Metadata-Version: 2.4
Name: llama-index-postprocessor-tei-rerank
Version: 0.4.2
Summary: llama-index postprocessor text embedding inference rerank integration
Author-email: Rohith Ramakrishnan <rrohith2001@gmail.com>
License-Expression: MIT
License-File: LICENSE
Requires-Python: <4.0,>=3.9
Requires-Dist: llama-index-core<0.15,>=0.13.0
